MYPACKAGEFORTEST/__init__.py
MYPACKAGEFORTEST/main.py
MyPackageForTest-0.0.1.dist-info/METADATA
MyPackageForTest-0.0.1.dist-info/WHEEL
MyPackageForTest-0.0.1.dist-info/top_level.txt
MyPackageForTest-0.0.1.dist-info/RECORD
