Metadata-Version: 2.1
Name: MyPackageForTest
Version: 0.0.1
Summary: Package for test
Home-page: UNKNOWN
Author: Me
Author-email: lapin.kirill45@gmail.com
License: UNKNOWN
Platform: UNKNOWN
Classifier: Programming Language :: Python :: 3.8
Classifier: License :: OSI Approved :: MIT License
Requires-Python: >=3.6
